{
  "recentFiles": [
    {
      "basename": "UBA",
      "path": "UBA.md"
    },
    {
      "basename": "Gestión del Desarrollo de Sistemas Informáticos",
      "path": "Gestión del Desarrollo de Sistemas Informáticos/Gestión del Desarrollo de Sistemas Informáticos.md"
    },
    {
      "basename": "Empresas de Base Tecnologica I",
      "path": "Empresas de Base Tecnológica I/Empresas de Base Tecnologica I.md"
    }
  ],
  "omittedPaths": [],
  "omittedTags": [],
  "updateOn": "file-open",
  "omitBookmarks": false
}