{
  "main": {
    "id": "6fcbf5d28feaf53a",
    "type": "split",
    "children": [
      {
        "id": "406bc2f47477702b",
        "type": "tabs",
        "children": [
          {
            "id": "02505ee49ea3f441",
            "type": "leaf",
            "state": {
              "type": "markdown",
              "state": {
                "file": "Física II/Física II.md",
                "mode": "source",
                "source": false
              }
            }
          },
          {
            "id": "44492f8b135c9430",
            "type": "leaf",
            "state": {
              "type": "markdown",
              "state": {
                "file": "Física II/1. Electroestática en el Vacío/1.0 Electroestática en el Vacío.md",
                "mode": "source",
                "source": false
              }
            }
          },
          {
            "id": "aa66fe974568cef0",
            "type": "leaf",
            "state": {
              "type": "markdown",
              "state": {
                "file": "Física II/1. Electroestática en el Vacío/1.1 Ley de Coulomb.md",
                "mode": "source",
                "source": false
              }
            }
          },
          {
            "id": "0555fef803af1d76",
            "type": "leaf",
            "state": {
              "type": "excalidraw",
              "state": {
                "file": "Física II/1. Electroestática en el Vacío/Campo Electrico Fuente.md"
              }
            }
          },
          {
            "id": "949f2d52cb90ec7d",
            "type": "leaf",
            "state": {
              "type": "markdown",
              "state": {
                "file": "Física II/1. Electroestática en el Vacío/1.2 Campo Eléctrico (caso electroestático Discreto).md",
                "mode": "source",
                "source": false
              }
            }
          }
        ],
        "currentTab": 4
      }
    ],
    "direction": "vertical"
  },
  "left": {
    "id": "a06b0f87ccd87252",
    "type": "split",
    "children": [
      {
        "id": "d3e668218d37f99c",
        "type": "tabs",
        "children": [
          {
            "id": "1f0ff475a551d0ff",
            "type": "leaf",
            "state": {
              "type": "file-explorer",
              "state": {
                "sortOrder": "alphabetical"
              }
            }
          },
          {
            "id": "332773528d4c7fa9",
            "type": "leaf",
            "state": {
              "type": "search",
              "state": {
                "query": "",
                "matchingCase": true,
                "explainSearch": false,
                "collapseAll": false,
                "extraContext": false,
                "sortOrder": "alphabetical"
              }
            }
          },
          {
            "id": "e00d2f83846b1c6f",
            "type": "leaf",
            "state": {
              "type": "starred",
              "state": {}
            }
          }
        ]
      }
    ],
    "direction": "horizontal",
    "width": 300
  },
  "right": {
    "id": "bb8a3eb3df49ac66",
    "type": "split",
    "children": [
      {
        "id": "f25f4516dde8df05",
        "type": "tabs",
        "children": [
          {
            "id": "bea7dcb4a257b4ac",
            "type": "leaf",
            "state": {
              "type": "backlink",
              "state": {
                "file": "Física II/1. Electroestática en el Vacío/1.2 Campo Eléctrico (caso electroestático Discreto).md",
                "collapseAll": false,
                "extraContext": false,
                "sortOrder": "alphabetical",
                "showSearch": false,
                "searchQuery": "",
                "backlinkCollapsed": false,
                "unlinkedCollapsed": true
              }
            }
          },
          {
            "id": "04810a1842f67df0",
            "type": "leaf",
            "state": {
              "type": "tag",
              "state": {
                "sortOrder": "frequency",
                "useHierarchy": true
              }
            }
          },
          {
            "id": "ade5cc5e7c3e2ebc",
            "type": "leaf",
            "state": {
              "type": "outline",
              "state": {
                "file": "Física II/1. Electroestática en el Vacío/1.2 Campo Eléctrico (caso electroestático Discreto).md"
              }
            }
          },
          {
            "id": "1be988f60aff20df",
            "type": "leaf",
            "state": {
              "type": "advanced-tables-toolbar",
              "state": {}
            }
          },
          {
            "id": "ad5c83cb01c7514a",
            "type": "leaf",
            "state": {
              "type": "online.louis01.ava",
              "state": {}
            }
          }
        ],
        "currentTab": 3
      }
    ],
    "direction": "horizontal",
    "width": 300,
    "collapsed": true
  },
  "left-ribbon": {
    "hiddenItems": {
      "table-editor-obsidian:Advanced Tables Toolbar": false,
      "obsidian-excalidraw-plugin:New Excalidraw drawing": false,
      "switcher:Open quick switcher": false,
      "graph:Open graph view": false,
      "canvas:Create new canvas": false,
      "command-palette:Open command palette": false,
      "markdown-importer:Open format converter": false
    }
  },
  "active": "949f2d52cb90ec7d",
  "lastOpenFiles": [
    "Física II/1. Electroestática en el Vacío/Campo Electrico Sumidero.md",
    "Física II/1. Electroestática en el Vacío/1.2 Campo Eléctrico (caso electroestático Discreto).md",
    "Física II/1. Electroestática en el Vacío/1.1 Ley de Coulomb.md",
    "Física II/1. Electroestática en el Vacío/Campo Electrico Fuente.md",
    "Pasted image 20230317102824.png",
    "Física II/1. Electroestática en el Vacío/1.0 Electroestática en el Vacío.md",
    "Física II/Física II.md",
    "Física II/0. Repaso/0.0 Repaso.md",
    "Física II/1. Electroestática en el Vacío",
    "Análisis Matemático II/Apuntes para Final.md",
    "Análisis Matemático II/13. Teoremas de Integrales/Teorema de Green.md",
    "Análisis Matemático II/13. Teoremas de Integrales/Teorema de la divergencia - Teorema de Gauss.md",
    "Análisis Matemático II/13. Teoremas de Integrales/Teorema del Stokes (Rotor).md",
    "Análisis Matemático II/13. Teoremas de Integrales/Rotor.md",
    "Análisis Matemático II/10. Integrales Triples/Cambios de Variable en Integrales Triples.md",
    "Pasted image 20230316104738.png",
    "Pasted image 20230316104340.png",
    "Pasted image 20230316104323.png",
    "Álgebra II/1. Espacios Vectoriales/1.2 Subespacios Vectoriales.md",
    "conflict-files-obsidian-git.md",
    "Álgebra II/6. DVS/Pseudoinversa de Moore-Penrose.md",
    "Álgebra II/6. DVS/6.0 DVS.md",
    "Álgebra II/6. DVS",
    "Álgebra II/5. Matrices Ortogonales, Unitarias, Simétricas y Hermíticas/Matrices Semejantes.md",
    "Álgebra II/5. Matrices Ortogonales, Unitarias, Simétricas y Hermíticas/Matrices Ortogonales.md",
    "Álgebra II/5. Matrices Ortogonales, Unitarias, Simétricas y Hermíticas/Matrices Equivalentes.md",
    "valor singular.md",
    "semidefinida positiva.md",
    "Untitled.canvas",
    "Untitled 2.canvas",
    "Untitled 1.canvas",
    "Imagenes/Pasted image 20221201223920.png",
    "Imagenes/Pasted image 20221201223849.png",
    "Imagenes/Pasted image 20221201223839.png",
    "Imagenes/Pasted image 20221201191333.png",
    "Imagenes/Pasted image 20221201190854.png",
    "Imagenes/Pasted image 20221201190836.png",
    "Física II/0. Repaso",
    "Física II",
    "4.4 Diferenciabilidad.md",
    "Álgebra II/1. Espacios Vectoriales/1.1 Definición de Espacio Vectorial.md",
    "Algoritmos y Programación III/8. Programación Funcional/8.5 Funciones de Primera Clase.md",
    "Análisis Matemático II/8.Ecuaciones Diferenciales/Curvas Ortogonales.md"
  ]
}